print_fortran_routines/__init__.py
print_fortran_routines-0.0.1.dist-info/LICENSE
print_fortran_routines-0.0.1.dist-info/METADATA
print_fortran_routines-0.0.1.dist-info/WHEEL
print_fortran_routines-0.0.1.dist-info/top_level.txt
print_fortran_routines-0.0.1.dist-info/RECORD
