Metadata-Version: 2.1
Name: print-fortran-routines
Version: 0.0.1
Summary: Prints names of subroutines in Fortran when they are called
Home-page: https://github.com/onfarrell/sampleproject
Author: E. Farrell
Author-email: efarrel4@tcd.ie
License: UNKNOWN
Platform: UNKNOWN
Classifier: Programming Language :: Python :: 3
Classifier: License :: OSI Approved :: MIT License
Classifier: Operating System :: OS Independent
Requires-Python: >=3.6
